count_time/__init__.py
count_time/count_time.py
report/__init__.py
report/report.py
Racing_report-0.0.1.dist-info/LICENSE
Racing_report-0.0.1.dist-info/METADATA
Racing_report-0.0.1.dist-info/WHEEL
Racing_report-0.0.1.dist-info/top_level.txt
Racing_report-0.0.1.dist-info/RECORD
